<?xml version="1.0" encoding="UTF-8"?>
<?xml-stylesheet type="text/xsl" href="http://lsst-sal.tuc.noao.edu/schema/SALEventSet.xsl"?>
<SALEventSet xmlns:xsi="http://www.w3.org/2001/XMLSchema-instance"
	xsi:noNamespaceSchemaLocation="http://lsst-sal.tuc.noao.edu/schema/SALEventSet.xsd">
<Enumeration>DetailedState_DisabledState,DetailedState_EnabledState,DetailedState_FaultState,DetailedState_OfflineState,DetailedState_StandbyState</Enumeration>

<SALEvent>
    <Subsystem>MTAlignment</Subsystem>
    <Version>3.7.1</Version>
    <Author></Author>
    <EFDB_Topic>MTAlignment_logevent_offsetsPublish</EFDB_Topic>
    <Alias>offsetsPublish</Alias>
    <Explanation>http://sal.lsst.org</Explanation>
    <item>
        <EFDB_Name>target</EFDB_Name>
        <Description>name of the object these offests belong to (M2, Camera, etc)</Description>
        <IDL_Type>string</IDL_Type>
        <Units>dimensionless</Units>
        <Count>1</Count>
    </item>
    <item>
        <EFDB_Name>dX</EFDB_Name>
        <Description>Measured object offset in the x-axis relative to nominal.</Description>
        <IDL_Type>float</IDL_Type>
        <Units>meter</Units>
        <Count>1</Count>
    </item>
    <item>
        <EFDB_Name>dY</EFDB_Name>
        <Description>Measured object offset in the y-axis relative to nominal.</Description>
        <IDL_Type>float</IDL_Type>
        <Units>meter</Units>
        <Count>1</Count>
    </item>
    <item>
        <EFDB_Name>dZ</EFDB_Name>
        <Description>Measured object offset in the z-axis relative to nominal.</Description>
        <IDL_Type>float</IDL_Type>
        <Units>meter</Units>
        <Count>1</Count>
    </item>
        <item>
        <EFDB_Name>dRX</EFDB_Name>
        <Description>Measured object rotation with respect to the x-axis relative to nominal</Description>
        <IDL_Type>float</IDL_Type>
        <Units>degree</Units>
        <Count>1</Count>
    </item>
    <item>
        <EFDB_Name>dRY</EFDB_Name>
        <Description>Measured object rotation with respect to the y-axis relative to nominal</Description>
        <IDL_Type>float</IDL_Type>
        <Units>degree</Units>
        <Count>1</Count>
    </item>
    <item>
        <EFDB_Name>dRZ</EFDB_Name>
        <Description>Measured object rotation with respect to the z-axis relative to nominal</Description>
        <IDL_Type>float</IDL_Type>
        <Units>degree</Units>
        <Count>1</Count>
    </item>
</SALEvent>
<SALEvent>
    <Subsystem>MTAlignment</Subsystem>
    <Version>3.7.1</Version>
    <Author></Author>
    <EFDB_Topic>MTAlignment_logevent_positionPublish</EFDB_Topic>
    <Alias>positionPublish</Alias>
    <Explanation>http://sal.lsst.org</Explanation>
    <item>
        <EFDB_Name>target</EFDB_Name>
        <Description>name of the object these positions belong to (M2, Camera, etc)</Description>
        <IDL_Type>string</IDL_Type>
        <Units>dimensionless</Units>
        <Count>1</Count>
    </item>
    <item>
        <EFDB_Name>dX</EFDB_Name>
        <Description>x positions of the measured object</Description>
        <IDL_Type>float</IDL_Type>
        <Units>meter</Units>
        <Count>1</Count>
    </item>
    <item>
        <EFDB_Name>dY</EFDB_Name>
        <Description>y positions of the measured object</Description>
        <IDL_Type>float</IDL_Type>
        <Units>meter</Units>
        <Count>1</Count>
    </item>
    <item>
        <EFDB_Name>dZ</EFDB_Name>
        <Description>z positions of the measured object</Description>
        <IDL_Type>float</IDL_Type>
        <Units>meter</Units>
        <Count>1</Count>
    </item>
        <item>
        <EFDB_Name>dRX</EFDB_Name>
        <Description>x rotation positions of the measured object</Description>
        <IDL_Type>float</IDL_Type>
        <Units>degree</Units>
        <Count>1</Count>
    </item>
    <item>
        <EFDB_Name>dRY</EFDB_Name>
        <Description>y rotation positions of the measured object</Description>
        <IDL_Type>float</IDL_Type>
        <Units>degree</Units>
        <Count>1</Count>
    </item>
    <item>
        <EFDB_Name>dRZ</EFDB_Name>
        <Description>z rotation positions of the measured object</Description>
        <IDL_Type>float</IDL_Type>
        <Units>degree</Units>
        <Count>1</Count>
    </item>
</SALEvent>
<SALEvent>
    <Subsystem>MTAlignment</Subsystem>
    <Version>3.7.1</Version>
    <Author></Author>
    <EFDB_Topic>MTAlignment_logevent_t2saError</EFDB_Topic>
    <Alias>t2saError</Alias>
    <Explanation>http://sal.lsst.org</Explanation>
    <item>
        <EFDB_Name>t2saError</EFDB_Name>
        <Description>Error code received from T2SA</Description>
        <IDL_Type>int</IDL_Type>
        <Units>dimensionless</Units>
        <Count>1</Count>
    </item>
</SALEvent>
</SALEventSet>
