<?xml version="1.0" encoding="UTF-8"?>
<?xml-stylesheet type="text/xsl" href="http://lsst-sal.tuc.noao.edu/schema/SALCommandSet.xsl"?>
<SALCommandSet xmlns:xsi="http://www.w3.org/2001/XMLSchema-instance"
	xsi:noNamespaceSchemaLocation="http://lsst-sal.tuc.noao.edu/schema/SALCommandSet.xsd">

<SALCommand>
 <Subsystem>tcs</Subsystem>
<Version>3.2.0</Version>
 <Author>salgenerator</Author>
 <EFDB_Topic>tcs_command_wfpCalculate</EFDB_Topic>
 <Alias>wfpCalculate</Alias>
 <Device>wfp</Device>
 <Property>zernikes</Property>
 <Action>calculate</Action>
 <Value></Value>
 <Explanation>http://sal.lsst.org/SAL/Commands/tcs_command_wfpCalculate.html</Explanation>
    <item>
      <EFDB_Name>uid</EFDB_Name>
      <Description> </Description>
       <IDL_Type>string</IDL_Type>
       <IDL_Size>64</IDL_Size>
      <Units> </Units>
      <Count>1</Count>
    </item>
</SALCommand>

<SALCommand>
 <Subsystem>tcs</Subsystem>
<Version>3.2.0</Version>
 <Author>salgenerator</Author>
 <EFDB_Topic>tcs_command_wfpSimulate</EFDB_Topic>
 <Alias>wfpSimulate</Alias>
 <Device>wfp</Device>
 <Property>zernikes</Property>
 <Action>simulate</Action>
 <Value></Value>
 <Explanation>http://sal.lsst.org/SAL/Commands/tcs_command_wfpSimulate.html</Explanation>
    <item>
      <EFDB_Name>uid</EFDB_Name>
      <Description> </Description>
       <IDL_Type>string</IDL_Type>
       <IDL_Size>64</IDL_Size>
      <Units> </Units>
      <Count>1</Count>
    </item>
    <item>
      <EFDB_Name>z_arr</EFDB_Name>
      <Description> </Description>
       <IDL_Type>double</IDL_Type>
      <Units> </Units>
      <Count>18</Count>
    </item>
</SALCommand>

<SALCommand>
 <Subsystem>tcs</Subsystem>
<Version>3.6.0</Version>
 <Author>aanania</Author>
 <EFDB_Topic>tcs_command_filterChangeRequest</EFDB_Topic>
 <Alias>filterChangeRequest</Alias>
 <Device></Device>
 <Property></Property>
 <Action></Action>
  <Value></Value>
 <Explanation>Move to required position to execute a filter change</Explanation>
    <item>
      <EFDB_Name>filterChangeRequest</EFDB_Name>
      <Description> </Description>
       <IDL_Type>string</IDL_Type>
	<IDL_Size>64</IDL_Size>
       <Units> </Units>
      <Count>1</Count>
    </item>
</SALCommand>

<SALCommand>
 <Subsystem>tcs</Subsystem>
<Version>3.6.0</Version>
 <Author>aanania</Author>
 <EFDB_Topic>tcs_command_stopMotion</EFDB_Topic>
 <Alias>stopMotion</Alias>
 <Device></Device>
 <Property></Property>
 <Action></Action>
 <Value></Value>
 <Explanation>Stop movion when in any motion state</Explanation>
    <item>
      <EFDB_Name>stopMotion</EFDB_Name>
      <Description> </Description>
       <IDL_Type>boolean</IDL_Type>
       <Units> </Units>
      <Count>1</Count>
    </item>
</SALCommand>

<SALCommand>
 <Subsystem>tcs</Subsystem>
<Version>3.6.0</Version>
 <Author>aanania</Author>
 <EFDB_Topic>tcs_command_target</EFDB_Topic>
 <Alias>target</Alias>
 <Device></Device>
 <Property></Property>
 <Action></Action>
 <Value></Value>
 <Explanation>Target to point the telescope</Explanation>
    <item>
      <EFDB_Name>targetId</EFDB_Name>
      <Description> </Description>
       <IDL_Type>long</IDL_Type>
       <Units> </Units>
      <Count>1</Count>
    </item>
    <item>
      <EFDB_Name>fieldId</EFDB_Name>
      <Description> </Description>
       <IDL_Type>long</IDL_Type>
       <Units> </Units>
      <Count>1</Count>
    </item>
    <item>
      <EFDB_Name>groupId</EFDB_Name>
      <Description> </Description>
       <IDL_Type>long</IDL_Type>
       <Units> </Units>
      <Count>1</Count>
    </item>
    <item>
      <EFDB_Name>filter</EFDB_Name>
      <Description> </Description>
       <IDL_Type>string</IDL_Type>
	<IDL_Size>64</IDL_Size>
       <Units> </Units>
      <Count>1</Count>
    </item>
    <item>
      <EFDB_Name>requestTime</EFDB_Name>
      <Description> </Description>
       <IDL_Type>double</IDL_Type>
       <Units> </Units>
      <Count>1</Count>
    </item>
    <item>
      <EFDB_Name>ra</EFDB_Name>
      <Description>Right ascension</Description>
       <IDL_Type>double</IDL_Type>
       <Units> </Units>
      <Count>1</Count>
    </item>
    <item>
      <EFDB_Name>decl</EFDB_Name>
      <Description>Declination</Description>
       <IDL_Type>double</IDL_Type>
       <Units> </Units>
      <Count>1</Count>
    </item>
    <item>
      <EFDB_Name>angle</EFDB_Name>
      <Description> </Description>
       <IDL_Type>double</IDL_Type>
       <Units> </Units>
      <Count>1</Count>
    </item>
    <item>
      <EFDB_Name>num_exposures</EFDB_Name>
      <Description> </Description>
       <IDL_Type>long</IDL_Type>
       <Units> </Units>
      <Count>1</Count>
    </item>
    <item>
      <EFDB_Name>exposure_times</EFDB_Name>
      <Description> </Description>
       <IDL_Type>long</IDL_Type>
       <Units> </Units>
      <Count>1</Count>
    </item>
    <item>
      <EFDB_Name>slew_time</EFDB_Name>
      <Description> </Description>
       <IDL_Type>double</IDL_Type>
       <Units> </Units>
      <Count>1</Count>
    </item>
</SALCommand>
</SALCommandSet>
